jupyterlab/__init__.py
jupyterlab/__main__.py
jupyterlab/_version.py
jupyterlab/browser-test.js
jupyterlab/browser_check.py
jupyterlab/commands.py
jupyterlab/coreconfig.py
jupyterlab/debuglog.py
jupyterlab/federated_labextensions.py
jupyterlab/jlpmapp.py
jupyterlab/labapp.py
jupyterlab/labextensions.py
jupyterlab/labhubapp.py
jupyterlab/node-version-check.js
jupyterlab/pytest_plugin.py
jupyterlab/semver.py
jupyterlab/serverextension.py
jupyterlab/style.js
jupyterlab/upgrade_extension.py
jupyterlab/utils.py
jupyterlab/handlers/__init__.py
jupyterlab/handlers/build_handler.py
jupyterlab/handlers/error_handler.py
jupyterlab/handlers/extension_manager_handler.py
jupyterlab/handlers/yjs_echo_ws.py
jupyterlab/schemas/@jupyterlab/application-extension/commands.json
jupyterlab/schemas/@jupyterlab/application-extension/context-menu.json
jupyterlab/schemas/@jupyterlab/application-extension/package.json.orig
jupyterlab/schemas/@jupyterlab/application-extension/sidebar.json
jupyterlab/schemas/@jupyterlab/apputils-extension/package.json.orig
jupyterlab/schemas/@jupyterlab/apputils-extension/palette.json
jupyterlab/schemas/@jupyterlab/apputils-extension/print.json
jupyterlab/schemas/@jupyterlab/apputils-extension/themes.json
jupyterlab/schemas/@jupyterlab/apputils-extension/workspaces.json
jupyterlab/schemas/@jupyterlab/codemirror-extension/commands.json
jupyterlab/schemas/@jupyterlab/codemirror-extension/package.json.orig
jupyterlab/schemas/@jupyterlab/completer-extension/consoles.json
jupyterlab/schemas/@jupyterlab/completer-extension/files.json
jupyterlab/schemas/@jupyterlab/completer-extension/notebooks.json
jupyterlab/schemas/@jupyterlab/completer-extension/package.json.orig
jupyterlab/schemas/@jupyterlab/console-extension/foreign.json
jupyterlab/schemas/@jupyterlab/console-extension/package.json.orig
jupyterlab/schemas/@jupyterlab/console-extension/tracker.json
jupyterlab/schemas/@jupyterlab/debugger-extension/main.json
skjupyterlab-3.3.0.dist-info/LICENSE
skjupyterlab-3.3.0.dist-info/METADATA
skjupyterlab-3.3.0.dist-info/WHEEL
skjupyterlab-3.3.0.dist-info/entry_points.txt
skjupyterlab-3.3.0.dist-info/top_level.txt
skjupyterlab-3.3.0.dist-info/RECORD
