Metadata-Version: 2.1
Name: skjupyterlab
Version: 3.3.0
Summary: JupyterLab computational environment
Home-page: https://jupyter.org
Author: Jupyter Development Team
Author-email: jupyter@googlegroups.com
Keywords: ipython,jupyter
Platform: Linux
Platform: Mac OS X
Platform: Windows
Classifier: Development Status :: 5 - Production/Stable
Classifier: Intended Audience :: Developers
Classifier: Intended Audience :: System Administrators
Classifier: Intended Audience :: Science/Research
Classifier: License :: OSI Approved :: BSD License
Classifier: Programming Language :: Python
Classifier: Programming Language :: Python :: 3.7
Classifier: Programming Language :: Python :: 3.8
Classifier: Programming Language :: Python :: 3.9
Classifier: Programming Language :: Python :: 3.10
Requires-Python: >=3.6
License-File: LICENSE
Requires-Dist: ipython
Requires-Dist: packaging
Requires-Dist: tornado>=6.1.0
Requires-Dist: jupyter-core
Requires-Dist: jupyterlab-server~=2.3
Requires-Dist: jupyter-server~=1.4
Requires-Dist: nbclassic~=0.2
Requires-Dist: jinja2>=2.1
Requires-Dist: jupyterlab-language-pack-zh-CN
Provides-Extra: test
Requires-Dist: coverage; extra == "test"
Requires-Dist: pytest>=6.0; extra == "test"
Requires-Dist: pytest-cov; extra == "test"
Requires-Dist: pytest-console-scripts; extra == "test"
Requires-Dist: pytest-check-links>=0.5; extra == "test"
Requires-Dist: jupyterlab-server[test]~=2.2; extra == "test"
Requires-Dist: requests; extra == "test"
Requires-Dist: requests-cache; extra == "test"
Requires-Dist: virtualenv; extra == "test"
Requires-Dist: check-manifest; extra == "test"
Provides-Extra: ui-tests
Requires-Dist: build; extra == "ui-tests"
